{
  "id": "iron-borough/freightline-ring",
  "name": "Freightline Ring",
  "tourId": "iron-borough",
  "author": "core",
  "version": 1,
  "lengthMeters": 1608,
  "laps": 1,
  "laneCount": 3,
  "weatherOptions": ["clear", "rain", "fog"],
  "difficulty": 2,
  "segments": [
    { "len": 240, "curve": 0, "grade": 0, "roadsideLeft": "light_pole", "roadsideRight": "sign_marker", "hazards": [] },
    { "len": 240, "curve": 0.1, "grade": 0, "roadsideLeft": "fence_post", "roadsideRight": "light_pole", "hazards": ["traffic_cone"] },
    { "len": 240, "curve": 0, "grade": 0.03, "roadsideLeft": "rock_boulder", "roadsideRight": "fence_post", "hazards": [] },
    { "len": 240, "curve": -0.12, "grade": -0.02, "roadsideLeft": "sign_marker", "roadsideRight": "rock_boulder", "hazards": [] },
    { "len": 288, "curve": 0.06, "grade": 0, "roadsideLeft": "light_pole", "roadsideRight": "fence_post", "hazards": [] },
    { "len": 360, "curve": 0, "grade": 0, "roadsideLeft": "fence_post", "roadsideRight": "light_pole", "hazards": [] }
  ],
  "checkpoints": [
    { "segmentIndex": 0, "label": "start" },
    { "segmentIndex": 2, "label": "freight-yard" },
    { "segmentIndex": 4, "label": "exchange" }
  ],
  "spawn": { "gridSlots": 12 }
}
